{
    "destination_addresses" : [
       "8211 Castlebrook Dr, Indianapolis, IN 46256, USA",
       "3116 Sunnylane Dr, Erie, PA 16505, USA",
       "12382 Center Ave, Conneaut Lake, PA 16316, USA",
       "4800 Kennywood Blvd, West Mifflin, PA 15122, USA",
       "700 Park Ave, Altoona, PA 16602, USA",
       "391 Knoebels Boulevard, PA-487, Elysburg, PA 17824, USA",
       "100 Hersheypark Dr, Hershey, PA 17033, USA",
       "3830 Dorney Park Rd, Allentown, PA 18104, USA",
       "1 Six Flags Blvd, Jackson Township, NJ 08527, USA"
    ],
    "origin_addresses" : [
       "8211 Castlebrook Dr, Indianapolis, IN 46256, USA",
       "3116 Sunnylane Dr, Erie, PA 16505, USA",
       "12382 Center Ave, Conneaut Lake, PA 16316, USA",
       "4800 Kennywood Blvd, West Mifflin, PA 15122, USA",
       "700 Park Ave, Altoona, PA 16602, USA",
       "391 Knoebels Boulevard, PA-487, Elysburg, PA 17824, USA",
       "100 Hersheypark Dr, Hershey, PA 17033, USA",
       "3830 Dorney Park Rd, Allentown, PA 18104, USA",
       "1 Six Flags Blvd, Jackson Township, NJ 08527, USA"
    ],
    "rows" : [
       {
          "elements" : [
             {
                "distance" : {
                   "text" : "1 m",
                   "value" : 0
                },
                "duration" : {
                   "text" : "1 min",
                   "value" : 0
                },
                "status" : "OK"
             },
             {
                "distance" : {
                   "text" : "660 km",
                   "value" : 660200
                },
                "duration" : {
                   "text" : "6 hours 14 mins",
                   "value" : 22443
                },
                "status" : "OK"
             },
             {
                "distance" : {
                   "text" : "636 km",
                   "value" : 635688
                },
                "duration" : {
                   "text" : "6 hours 9 mins",
                   "value" : 22163
                },
                "status" : "OK"
             },
             {
                "distance" : {
                   "text" : "596 km",
                   "value" : 596347
                },
                "duration" : {
                   "text" : "5 hours 48 mins",
                   "value" : 20882
                },
                "status" : "OK"
             },
             {
                "distance" : {
                   "text" : "737 km",
                   "value" : 737450
                },
                "duration" : {
                   "text" : "7 hours 13 mins",
                   "value" : 25993
                },
                "status" : "OK"
             },
             {
                "distance" : {
                   "text" : "953 km",
                   "value" : 953131
                },
                "duration" : {
                   "text" : "8 hours 58 mins",
                   "value" : 32289
                },
                "status" : "OK"
             },
             {
                "distance" : {
                   "text" : "896 km",
                   "value" : 895539
                },
                "duration" : {
                   "text" : "8 hours 39 mins",
                   "value" : 31153
                },
                "status" : "OK"
             },
             {
                "distance" : {
                   "text" : "999 km",
                   "value" : 998903
                },
                "duration" : {
                   "text" : "9 hours 40 mins",
                   "value" : 34810
                },
                "status" : "OK"
             },
             {
                "distance" : {
                   "text" : "1,106 km",
                   "value" : 1106479
                },
                "duration" : {
                   "text" : "10 hours 34 mins",
                   "value" : 38027
                },
                "status" : "OK"
             }
          ]
       },
       {
          "elements" : [
             {
                "distance" : {
                   "text" : "657 km",
                   "value" : 656992
                },
                "duration" : {
                   "text" : "6 hours 11 mins",
                   "value" : 22258
                },
                "status" : "OK"
             },
             {
                "distance" : {
                   "text" : "1 m",
                   "value" : 0
                },
                "duration" : {
                   "text" : "1 min",
                   "value" : 0
                },
                "status" : "OK"
             },
             {
                "distance" : {
                   "text" : "70.4 km",
                   "value" : 70354
                },
                "duration" : {
                   "text" : "50 mins",
                   "value" : 2978
                },
                "status" : "OK"
             },
             {
                "distance" : {
                   "text" : "221 km",
                   "value" : 220528
                },
                "duration" : {
                   "text" : "2 hours 12 mins",
                   "value" : 7896
                },
                "status" : "OK"
             },
             {
                "distance" : {
                   "text" : "320 km",
                   "value" : 319676
                },
                "duration" : {
                   "text" : "3 hours 21 mins",
                   "value" : 12079
                },
                "status" : "OK"
             },
             {
                "distance" : {
                   "text" : "462 km",
                   "value" : 461940
                },
                "duration" : {
                   "text" : "4 hours 25 mins",
                   "value" : 15918
                },
                "status" : "OK"
             },
             {
                "distance" : {
                   "text" : "502 km",
                   "value" : 501882
                },
                "duration" : {
                   "text" : "5 hours 0 mins",
                   "value" : 18006
                },
                "status" : "OK"
             },
             {
                "distance" : {
                   "text" : "593 km",
                   "value" : 593037
                },
                "duration" : {
                   "text" : "5 hours 37 mins",
                   "value" : 20193
                },
                "status" : "OK"
             },
             {
                "distance" : {
                   "text" : "734 km",
                   "value" : 733663
                },
                "duration" : {
                   "text" : "6 hours 57 mins",
                   "value" : 24992
                },
                "status" : "OK"
             }
          ]
       },
       {
          "elements" : [
             {
                "distance" : {
                   "text" : "633 km",
                   "value" : 632550
                },
                "duration" : {
                   "text" : "6 hours 6 mins",
                   "value" : 21947
                },
                "status" : "OK"
             },
             {
                "distance" : {
                   "text" : "71.1 km",
                   "value" : 71128
                },
                "duration" : {
                   "text" : "50 mins",
                   "value" : 3004
                },
                "status" : "OK"
             },
             {
                "distance" : {
                   "text" : "1 m",
                   "value" : 0
                },
                "duration" : {
                   "text" : "1 min",
                   "value" : 0
                },
                "status" : "OK"
             },
             {
                "distance" : {
                   "text" : "168 km",
                   "value" : 168122
                },
                "duration" : {
                   "text" : "1 hour 46 mins",
                   "value" : 6359
                },
                "status" : "OK"
             },
             {
                "distance" : {
                   "text" : "267 km",
                   "value" : 267270
                },
                "duration" : {
                   "text" : "2 hours 56 mins",
                   "value" : 10543
                },
                "status" : "OK"
             },
             {
                "distance" : {
                   "text" : "410 km",
                   "value" : 409534
                },
                "duration" : {
                   "text" : "4 hours 0 mins",
                   "value" : 14381
                },
                "status" : "OK"
             },
             {
                "distance" : {
                   "text" : "449 km",
                   "value" : 449476
                },
                "duration" : {
                   "text" : "4 hours 34 mins",
                   "value" : 16469
                },
                "status" : "OK"
             },
             {
                "distance" : {
                   "text" : "541 km",
                   "value" : 540631
                },
                "duration" : {
                   "text" : "5 hours 11 mins",
                   "value" : 18656
                },
                "status" : "OK"
             },
             {
                "distance" : {
                   "text" : "681 km",
                   "value" : 681257
                },
                "duration" : {
                   "text" : "6 hours 31 mins",
                   "value" : 23456
                },
                "status" : "OK"
             }
          ]
       },
       {
          "elements" : [
             {
                "distance" : {
                   "text" : "595 km",
                   "value" : 595099
                },
                "duration" : {
                   "text" : "5 hours 46 mins",
                   "value" : 20785
                },
                "status" : "OK"
             },
             {
                "distance" : {
                   "text" : "220 km",
                   "value" : 220332
                },
                "duration" : {
                   "text" : "2 hours 12 mins",
                   "value" : 7913
                },
                "status" : "OK"
             },
             {
                "distance" : {
                   "text" : "167 km",
                   "value" : 167348
                },
                "duration" : {
                   "text" : "1 hour 46 mins",
                   "value" : 6338
                },
                "status" : "OK"
             },
             {
                "distance" : {
                   "text" : "1 m",
                   "value" : 0
                },
                "duration" : {
                   "text" : "1 min",
                   "value" : 0
                },
                "status" : "OK"
             },
             {
                "distance" : {
                   "text" : "148 km",
                   "value" : 148465
                },
                "duration" : {
                   "text" : "1 hour 47 mins",
                   "value" : 6441
                },
                "status" : "OK"
             },
             {
                "distance" : {
                   "text" : "358 km",
                   "value" : 358135
                },
                "duration" : {
                   "text" : "3 hours 47 mins",
                   "value" : 13646
                },
                "status" : "OK"
             },
             {
                "distance" : {
                   "text" : "327 km",
                   "value" : 327402
                },
                "duration" : {
                   "text" : "3 hours 27 mins",
                   "value" : 12424
                },
                "status" : "OK"
             },
             {
                "distance" : {
                   "text" : "431 km",
                   "value" : 430767
                },
                "duration" : {
                   "text" : "4 hours 28 mins",
                   "value" : 16081
                },
                "status" : "OK"
             },
             {
                "distance" : {
                   "text" : "538 km",
                   "value" : 538342
                },
                "duration" : {
                   "text" : "5 hours 22 mins",
                   "value" : 19298
                },
                "status" : "OK"
             }
          ]
       },
       {
          "elements" : [
             {
                "distance" : {
                   "text" : "734 km",
                   "value" : 734479
                },
                "duration" : {
                   "text" : "7 hours 12 mins",
                   "value" : 25920
                },
                "status" : "OK"
             },
             {
                "distance" : {
                   "text" : "320 km",
                   "value" : 320402
                },
                "duration" : {
                   "text" : "3 hours 23 mins",
                   "value" : 12181
                },
                "status" : "OK"
             },
             {
                "distance" : {
                   "text" : "267 km",
                   "value" : 267417
                },
                "duration" : {
                   "text" : "2 hours 57 mins",
                   "value" : 10605
                },
                "status" : "OK"
             },
             {
                "distance" : {
                   "text" : "148 km",
                   "value" : 147726
                },
                "duration" : {
                   "text" : "1 hour 49 mins",
                   "value" : 6536
                },
                "status" : "OK"
             },
             {
                "distance" : {
                   "text" : "1 m",
                   "value" : 0
                },
                "duration" : {
                   "text" : "1 min",
                   "value" : 0
                },
                "status" : "OK"
             },
             {
                "distance" : {
                   "text" : "212 km",
                   "value" : 212250
                },
                "duration" : {
                   "text" : "2 hours 5 mins",
                   "value" : 7527
                },
                "status" : "OK"
             },
             {
                "distance" : {
                   "text" : "230 km",
                   "value" : 229846
                },
                "duration" : {
                   "text" : "2 hours 21 mins",
                   "value" : 8449
                },
                "status" : "OK"
             },
             {
                "distance" : {
                   "text" : "328 km",
                   "value" : 327815
                },
                "duration" : {
                   "text" : "3 hours 15 mins",
                   "value" : 11715
                },
                "status" : "OK"
             },
             {
                "distance" : {
                   "text" : "445 km",
                   "value" : 444776
                },
                "duration" : {
                   "text" : "4 hours 16 mins",
                   "value" : 15369
                },
                "status" : "OK"
             }
          ]
       },
       {
          "elements" : [
             {
                "distance" : {
                   "text" : "951 km",
                   "value" : 950614
                },
                "duration" : {
                   "text" : "8 hours 55 mins",
                   "value" : 32094
                },
                "status" : "OK"
             },
             {
                "distance" : {
                   "text" : "462 km",
                   "value" : 461946
                },
                "duration" : {
                   "text" : "4 hours 26 mins",
                   "value" : 15930
                },
                "status" : "OK"
             },
             {
                "distance" : {
                   "text" : "409 km",
                   "value" : 408962
                },
                "duration" : {
                   "text" : "3 hours 59 mins",
                   "value" : 14355
                },
                "status" : "OK"
             },
             {
                "distance" : {
                   "text" : "358 km",
                   "value" : 358317
                },
                "duration" : {
                   "text" : "3 hours 50 mins",
                   "value" : 13805
                },
                "status" : "OK"
             },
             {
                "distance" : {
                   "text" : "214 km",
                   "value" : 213952
                },
                "duration" : {
                   "text" : "2 hours 7 mins",
                   "value" : 7628
                },
                "status" : "OK"
             },
             {
                "distance" : {
                   "text" : "1 m",
                   "value" : 0
                },
                "duration" : {
                   "text" : "1 min",
                   "value" : 0
                },
                "status" : "OK"
             },
             {
                "distance" : {
                   "text" : "103 km",
                   "value" : 103488
                },
                "duration" : {
                   "text" : "1 hour 13 mins",
                   "value" : 4359
                },
                "status" : "OK"
             },
             {
                "distance" : {
                   "text" : "118 km",
                   "value" : 118427
                },
                "duration" : {
                   "text" : "1 hour 36 mins",
                   "value" : 5781
                },
                "status" : "OK"
             },
             {
                "distance" : {
                   "text" : "262 km",
                   "value" : 261818
                },
                "duration" : {
                   "text" : "2 hours 59 mins",
                   "value" : 10762
                },
                "status" : "OK"
             }
          ]
       },
       {
          "elements" : [
             {
                "distance" : {
                   "text" : "892 km",
                   "value" : 892432
                },
                "duration" : {
                   "text" : "8 hours 37 mins",
                   "value" : 31002
                },
                "status" : "OK"
             },
             {
                "distance" : {
                   "text" : "496 km",
                   "value" : 496100
                },
                "duration" : {
                   "text" : "5 hours 0 mins",
                   "value" : 18007
                },
                "status" : "OK"
             },
             {
                "distance" : {
                   "text" : "443 km",
                   "value" : 443116
                },
                "duration" : {
                   "text" : "4 hours 34 mins",
                   "value" : 16432
                },
                "status" : "OK"
             },
             {
                "distance" : {
                   "text" : "327 km",
                   "value" : 326778
                },
                "duration" : {
                   "text" : "3 hours 28 mins",
                   "value" : 12455
                },
                "status" : "OK"
             },
             {
                "distance" : {
                   "text" : "231 km",
                   "value" : 230879
                },
                "duration" : {
                   "text" : "2 hours 21 mins",
                   "value" : 8469
                },
                "status" : "OK"
             },
             {
                "distance" : {
                   "text" : "107 km",
                   "value" : 107327
                },
                "duration" : {
                   "text" : "1 hour 17 mins",
                   "value" : 4619
                },
                "status" : "OK"
             },
             {
                "distance" : {
                   "text" : "1 m",
                   "value" : 0
                },
                "duration" : {
                   "text" : "1 min",
                   "value" : 0
                },
                "status" : "OK"
             },
             {
                "distance" : {
                   "text" : "116 km",
                   "value" : 116479
                },
                "duration" : {
                   "text" : "1 hour 17 mins",
                   "value" : 4629
                },
                "status" : "OK"
             },
             {
                "distance" : {
                   "text" : "222 km",
                   "value" : 221789
                },
                "duration" : {
                   "text" : "2 hours 19 mins",
                   "value" : 8348
                },
                "status" : "OK"
             }
          ]
       },
       {
          "elements" : [
             {
                "distance" : {
                   "text" : "995 km",
                   "value" : 995254
                },
                "duration" : {
                   "text" : "9 hours 35 mins",
                   "value" : 34506
                },
                "status" : "OK"
             },
             {
                "distance" : {
                   "text" : "591 km",
                   "value" : 591066
                },
                "duration" : {
                   "text" : "5 hours 37 mins",
                   "value" : 20246
                },
                "status" : "OK"
             },
             {
                "distance" : {
                   "text" : "538 km",
                   "value" : 538082
                },
                "duration" : {
                   "text" : "5 hours 11 mins",
                   "value" : 18671
                },
                "status" : "OK"
             },
             {
                "distance" : {
                   "text" : "430 km",
                   "value" : 429600
                },
                "duration" : {
                   "text" : "4 hours 26 mins",
                   "value" : 15959
                },
                "status" : "OK"
             },
             {
                "distance" : {
                   "text" : "328 km",
                   "value" : 328479
                },
                "duration" : {
                   "text" : "3 hours 14 mins",
                   "value" : 11661
                },
                "status" : "OK"
             },
             {
                "distance" : {
                   "text" : "118 km",
                   "value" : 118190
                },
                "duration" : {
                   "text" : "1 hour 36 mins",
                   "value" : 5787
                },
                "status" : "OK"
             },
             {
                "distance" : {
                   "text" : "113 km",
                   "value" : 113125
                },
                "duration" : {
                   "text" : "1 hour 15 mins",
                   "value" : 4496
                },
                "status" : "OK"
             },
             {
                "distance" : {
                   "text" : "1 m",
                   "value" : 0
                },
                "duration" : {
                   "text" : "1 min",
                   "value" : 0
                },
                "status" : "OK"
             },
             {
                "distance" : {
                   "text" : "152 km",
                   "value" : 152391
                },
                "duration" : {
                   "text" : "1 hour 36 mins",
                   "value" : 5732
                },
                "status" : "OK"
             }
          ]
       },
       {
          "elements" : [
             {
                "distance" : {
                   "text" : "1,104 km",
                   "value" : 1103763
                },
                "duration" : {
                   "text" : "10 hours 29 mins",
                   "value" : 37725
                },
                "status" : "OK"
             },
             {
                "distance" : {
                   "text" : "732 km",
                   "value" : 731939
                },
                "duration" : {
                   "text" : "6 hours 54 mins",
                   "value" : 24825
                },
                "status" : "OK"
             },
             {
                "distance" : {
                   "text" : "679 km",
                   "value" : 678955
                },
                "duration" : {
                   "text" : "6 hours 27 mins",
                   "value" : 23249
                },
                "status" : "OK"
             },
             {
                "distance" : {
                   "text" : "538 km",
                   "value" : 538109
                },
                "duration" : {
                   "text" : "5 hours 20 mins",
                   "value" : 19178
                },
                "status" : "OK"
             },
             {
                "distance" : {
                   "text" : "444 km",
                   "value" : 443920
                },
                "duration" : {
                   "text" : "4 hours 14 mins",
                   "value" : 15229
                },
                "status" : "OK"
             },
             {
                "distance" : {
                   "text" : "261 km",
                   "value" : 261129
                },
                "duration" : {
                   "text" : "2 hours 58 mins",
                   "value" : 10684
                },
                "status" : "OK"
             },
             {
                "distance" : {
                   "text" : "223 km",
                   "value" : 222601
                },
                "duration" : {
                   "text" : "2 hours 19 mins",
                   "value" : 8310
                },
                "status" : "OK"
             },
             {
                "distance" : {
                   "text" : "153 km",
                   "value" : 153295
                },
                "duration" : {
                   "text" : "1 hour 33 mins",
                   "value" : 5576
                },
                "status" : "OK"
             },
             {
                "distance" : {
                   "text" : "1 m",
                   "value" : 0
                },
                "duration" : {
                   "text" : "1 min",
                   "value" : 0
                },
                "status" : "OK"
             }
          ]
       }
    ],
    "status" : "OK"
 }